queueman/__init__.py
queueman/decorator.py
queueman/exceptions.py
queueman/helper.py
queueman/manager.py
queueman-0.4.dist-info/LICENCE
queueman-0.4.dist-info/METADATA
queueman-0.4.dist-info/WHEEL
queueman-0.4.dist-info/top_level.txt
queueman-0.4.dist-info/RECORD
