Metadata-Version: 2.1
Name: queueman
Version: 0.4
Summary: UNKNOWN
Home-page: https://github.com/ludeeus/queueman
Author: Joakim Sorensen
Author-email: hi@ludeeus.dev
License: UNKNOWN
Platform: UNKNOWN
Classifier: Programming Language :: Python :: 3
Classifier: License :: OSI Approved :: MIT License
Classifier: Operating System :: OS Independent
